botstudio_sdk/__init__.py
botstudio_sdk/example.py
botstudio_sdk/text.py
botstudio_sdk/api/__init__.py
botstudio_sdk/api/bag/__init__.py
botstudio_sdk/api/bag/code.py
botstudio_sdk/api/google/__init__.py
botstudio_sdk/api/google/analytics/__init__.py
botstudio_sdk/api/google/analytics/code.py
botstudio_sdk/api/google/maps/__init__.py
botstudio_sdk/api/google/maps/code.py
botstudio_sdk/api/google/sheets/__init__.py
botstudio_sdk/api/google/sheets/code.py
botstudio_sdk/api/tiledesk/__init__.py
botstudio_sdk/api/tiledesk/code.py
botstudio_sdk/dataclasses/__init__.py
botstudio_sdk/helpers/Prijsijst - prijslijst totaal.csv
botstudio_sdk/helpers/__init__.py
botstudio_sdk/helpers/csv_to_dict.py
botstudio_sdk/helpers/prijslijst.py
botstudio_sdk/tiledesk/__init__.py
botstudio_sdk-0.0.25.dist-info/METADATA
botstudio_sdk-0.0.25.dist-info/WHEEL
botstudio_sdk-0.0.25.dist-info/licenses/LICENSE
botstudio_sdk-0.0.25.dist-info/RECORD
