Metadata-Version: 2.1
Name: botstudio-sdk
Version: 0.0.25
Summary: A small example package
Project-URL: Homepage, https://github.com/botstudiotech/pip_package
Project-URL: Bug Tracker, https://github.com/botstudiotech/pip_package/issues
Author-email: Johan1us <info@botstudio.tech>
License-File: LICENSE
Classifier: License :: OSI Approved :: MIT License
Classifier: Operating System :: OS Independent
Classifier: Programming Language :: Python :: 3
Requires-Python: >=3.6
Requires-Dist: google-api-python-client==2.65.0
Requires-Dist: rasa-sdk==2.8.8
Requires-Dist: rasa==2.8.31
